ndfilters/__init__.py
ndfilters/_convolve.py
ndfilters/_generic.py
ndfilters/_indices.py
ndfilters/_mean.py
ndfilters/_median.py
ndfilters/_trimmed_mean.py
ndfilters/_variance.py
ndfilters/_tests/__init__.py
ndfilters/_tests/test_convolve.py
ndfilters/_tests/test_generic.py
ndfilters/_tests/test_mean.py
ndfilters/_tests/test_median.py
ndfilters/_tests/test_trimmed_mean.py
ndfilters/_tests/test_variance.py
ndfilters-0.4.1.dist-info/METADATA
ndfilters-0.4.1.dist-info/WHEEL
ndfilters-0.4.1.dist-info/top_level.txt
ndfilters-0.4.1.dist-info/RECORD
