Metadata-Version: 2.4
Name: ndfilters
Version: 0.4.1
Summary: Similar to the filters in `scipy.ndimage` but accelerated using Numba
Author-email: "Roy T. Smart" <roytsmart@gmail.com>
Project-URL: Homepage, https://github.com/sun-data/ndfilters
Project-URL: Documentation, https://ndfilters.readthedocs.io/en/latest
Classifier: Programming Language :: Python :: 3
Requires-Python: >=3.10
Requires-Dist: numpy
Requires-Dist: numba
Requires-Dist: astropy
Provides-Extra: test
Requires-Dist: pytest; extra == "test"
Requires-Dist: scipy; extra == "test"
Requires-Dist: astropy; extra == "test"
Provides-Extra: doc
Requires-Dist: pytest; extra == "doc"
Requires-Dist: scipy; extra == "doc"
Requires-Dist: pooch; extra == "doc"
Requires-Dist: matplotlib; extra == "doc"
Requires-Dist: graphviz; extra == "doc"
Requires-Dist: sphinx-autodoc-typehints; extra == "doc"
Requires-Dist: pydata-sphinx-theme; extra == "doc"
Requires-Dist: ipykernel; extra == "doc"
Requires-Dist: jupyter-sphinx; extra == "doc"
Requires-Dist: sphinx-favicon; extra == "doc"
